domain_admin/__init__.py
domain_admin/log.py
domain_admin/main.py
domain_admin/version.py
domain_admin/api/__init__.py
domain_admin/api/address_api.py
domain_admin/api/auth_api.py
domain_admin/api/cert_api.py
domain_admin/api/domain_api.py
domain_admin/api/domain_info_api.py
domain_admin/api/group_api.py
domain_admin/api/ip_api.py
domain_admin/api/log_scheduler_api.py
domain_admin/api/notify_api.py
domain_admin/api/system_api.py
domain_admin/api/user_api.py
domain_admin/api/whois_api.py
domain_admin/config/__init__.py
domain_admin/config/default_config.py
domain_admin/config/env_config.py
domain_admin/enums/__init__.py
domain_admin/enums/config_key_enum.py
domain_admin/enums/event_enum.py
domain_admin/enums/notify_type_enum.py
domain_admin/enums/status_enum.py
domain_admin/enums/version_enum.py
domain_admin/migrate/__init__.py
domain_admin/migrate/migrate_102_to_103.py
domain_admin/migrate/migrate_106_to_110.py
domain_admin/migrate/migrate_110_to_1212.py
domain_admin/migrate/migrate_1212_to_1213.py
domain_admin/migrate/migrate_1213_to_131.py
domain_admin/migrate/migrate_136_to_140_alpha.py
domain_admin/migrate/migrate_140_alpha_to_140.py
domain_admin/migrate/migrate_common.py
domain_admin/model/__init__.py
domain_admin/model/address_model.py
domain_admin/model/base_model.py
domain_admin/model/cache_domain_info_model.py
domain_admin/model/database.py
domain_admin/model/domain_info_model.py
domain_admin/model/domain_model.py
domain_admin/model/group_model.py
domain_admin/model/log_scheduler_model.py
domain_admin/model/notify_model.py
domain_admin/model/system_model.py
domain_admin/model/user_model.py
domain_admin/model/version_model.py
domain_admin/public/favicon.ico
domain_admin/public/index.html
domain_admin/public/css/ConditionFilterGroup.a91875e6.css
domain_admin/public/css/index.8a4026dd.css
domain_admin/public/css/index.eb5392c5.css
domain_admin/public/js/ConditionFilterGroup.e77466f4.js
domain_admin/public/js/ConnectStatus.422775f5.js
sayhi_admin-1.4.3.dist-info/LICENSE
sayhi_admin-1.4.3.dist-info/METADATA
sayhi_admin-1.4.3.dist-info/WHEEL
sayhi_admin-1.4.3.dist-info/top_level.txt
sayhi_admin-1.4.3.dist-info/zip-safe
sayhi_admin-1.4.3.dist-info/RECORD
