Metadata-Version: 2.1
Name: sayhi-admin
Version: 1.4.3
Summary: an admin for sayhi(this is fork demo)
Home-page: https://github.com/MeDeity/domain-admin.git
Author: Peng Shiyu
Author-email: pengshiyuyx@gmail.com
License: MIT
Keywords: an admin for sayhi
Classifier: Programming Language :: Python :: 3.7
License-File: LICENSE
Requires-Dist: requests ==2.28.1
Requires-Dist: Flask ==2.2.2
Requires-Dist: werkzeug ==2.2.2
Requires-Dist: Jinja2 ==3.0.0
Requires-Dist: Flask-Cors ==3.0.10
Requires-Dist: peewee ==3.15.3
Requires-Dist: python-dateutil ==2.8.2
Requires-Dist: gunicorn ==20.1.0
Requires-Dist: apscheduler ==3.9.1
Requires-Dist: PyJWT ==2.5.0
Requires-Dist: bcrypt ==4.0.0
Requires-Dist: python-dotenv ==0.21.0
Requires-Dist: pyOpenSSL ==22.1.0
Requires-Dist: tldextract ==3.4.0
Requires-Dist: environs ==9.5.0
Requires-Dist: pymysql ==1.0.3
